Metadata-Version: 1.0
Name: Distributions-N-G
Version: 0.1
Summary: Gaussian distributions
Home-page: UNKNOWN
Author: Basil ELdho
Author-email: UNKNOWN
License: UNKNOWN
Platform: UNKNOWN
